mapbox_location/__init__.py
mapbox_location/viz.py
mapbox_location/templates/map.html
mapbox_location-1.0.3.dist-info/METADATA
mapbox_location-1.0.3.dist-info/WHEEL
mapbox_location-1.0.3.dist-info/top_level.txt
mapbox_location-1.0.3.dist-info/RECORD
